pydl/__init__.py
pydl/conftest.py
pydl/file_lines.py
pydl/median.py
pydl/pcomp.py
pydl/rebin.py
pydl/smooth.py
pydl/uniq.py
pydl/version.py
pydl/goddard/__init__.py
pydl/goddard/astro.py
pydl/goddard/math.py
pydl/goddard/misc.py
pydl/goddard/tests/__init__.py
pydl/goddard/tests/test_goddard.py
pydl/photoop/__init__.py
pydl/photoop/image.py
pydl/photoop/photoobj.py
pydl/photoop/sdssio.py
pydl/photoop/window.py
pydl/photoop/tests/__init__.py
pydl/photoop/tests/test_image.py
pydl/photoop/tests/test_photoop.py
pydl/photoop/tests/test_sdssio.py
pydl/photoop/tests/test_window.py
pydl/photoop/tests/t/psField-003366-3-0110.fit
pydl/pydlspec2d/__init__.py
pydl/pydlspec2d/spec1d.py
pydl/pydlspec2d/spec2d.py
pydl/pydlspec2d/tests/__init__.py
pydl/pydlspec2d/tests/test_spec1d.py
pydl/pydlspec2d/tests/test_spec2d.py
pydl/pydlspec2d/tests/t/filter_thru_idl_data.txt
pydl/pydlspec2d/tests/t/spPlate-4055-55359-0020.fits
pydl/pydlspec2d/tests/t/test_template_metadata.par
pydl/pydlutils/__init__.py
pydl/pydlutils/bspline.py
pydl/pydlutils/cooling.py
pydl/pydlutils/coord.py
pydl/pydlutils/image.py
pydl/pydlutils/mangle.py
pydl/pydlutils/math.py
pydl/pydlutils/misc.py
pydl/pydlutils/rgbcolor.py
pydl/pydlutils/sdss.py
pydl/pydlutils/spheregroup.py
pydl/pydlutils/trace.py
pydl/pydlutils/yanny.py
pydl/pydlutils/data/cooling/README.rst
pydl/pydlutils/data/cooling/cooling.sha1sum
pydl/pydlutils/data/cooling/m+05.cie
pydl/pydlutils/data/cooling/m-00.cie
pydl/pydlutils/data/cooling/m-05.cie
pydl/pydlutils/data/cooling/m-10.cie
pydl/pydlutils/data/cooling/m-15.cie
pydl/pydlutils/data/cooling/m-20.cie
pydl/pydlutils/data/cooling/m-30.cie
pydl/pydlutils/data/cooling/mzero.cie
pydl/pydlutils/data/filters/sdss_jun2001_g_atm.dat
pydl/pydlutils/data/filters/sdss_jun2001_i_atm.dat
pydl/pydlutils/data/filters/sdss_jun2001_r_atm.dat
pydl/pydlutils/data/filters/sdss_jun2001_u_atm.dat
pydl/pydlutils/data/filters/sdss_jun2001_z_atm.dat
pydl/pydlutils/tests/__init__.py
pydl/pydlutils/tests/test_bspline.py
pydl-1.0.1.dist-info/LICENSE.rst
pydl-1.0.1.dist-info/METADATA
pydl-1.0.1.dist-info/WHEEL
pydl-1.0.1.dist-info/entry_points.txt
pydl-1.0.1.dist-info/top_level.txt
pydl-1.0.1.dist-info/RECORD
