Metadata-Version: 2.1
Name: pydl
Version: 1.0.1
Summary: Library of IDL astronomy routines converted to Python.
Home-page: https://github.com/weaverba137/pydl
Author: Benjamin Alan Weaver
Author-email: benjamin.weaver@noirlab.edu
License: BSD 3-Clause License
Classifier: Development Status :: 5 - Production/Stable
Classifier: Environment :: Console
Classifier: Intended Audience :: Science/Research
Classifier: License :: OSI Approved :: BSD License
Classifier: Operating System :: OS Independent
Classifier: Programming Language :: Python :: 3
Classifier: Topic :: Scientific/Engineering :: Physics
Classifier: Topic :: Scientific/Engineering :: Astronomy
Requires-Python: >=3.8
License-File: LICENSE.rst
Requires-Dist: astropy >=5.0
Requires-Dist: scipy >=1.3
Provides-Extra: all
Requires-Dist: matplotlib ; extra == 'all'
Provides-Extra: docs
Requires-Dist: sphinx-astropy ; extra == 'docs'
Provides-Extra: test
Requires-Dist: pytest-astropy ; extra == 'test'
Requires-Dist: pytest-mock ; extra == 'test'
Requires-Dist: tox ; extra == 'test'
